xspin/__init__.py
xspin/__init__.pyi
xspin-1.0.2.dist-info/LICENSE
xspin-1.0.2.dist-info/METADATA
xspin-1.0.2.dist-info/WHEEL
xspin-1.0.2.dist-info/top_level.txt
xspin-1.0.2.dist-info/RECORD
