Metadata-Version: 2.1
Name: xspin
Version: 1.0.2
Summary: Python module for creating console spinners.
License: MIT License
Project-URL: homepage, https://github.com/glamorie/xspin
Project-URL: documentation, https://github.com/glamorie/xspin
Project-URL: repository, https://github.com/glamorie/xspin
Project-URL: changelog, https://github.com/glamorie/xspin/releases
Keywords: console,terminal,cli,python,commandline,spinners,utilites
Classifier: Development Status :: 3 - Alpha
Classifier: Intended Audience :: Developers
Classifier: Topic :: Software Development :: Libraries
Classifier: Topic :: Terminals
Classifier: Topic :: Utilities
Classifier: Environment :: Console
Classifier: Programming Language :: Python :: 3
Classifier: Programming Language :: Python :: 3.7
Classifier: Programming Language :: Python :: 3.8
Classifier: Programming Language :: Python :: 3.9
Classifier: Programming Language :: Python :: 3.10
Classifier: License :: OSI Approved :: MIT License
Classifier: Operating System :: OS Independent
License-File: LICENSE
Provides-Extra: dev
Requires-Dist: toml; extra == "dev"
